huster/SimpleHTTPServerWithUpload_py2.py
huster/SimpleHTTPServerWithUpload_py3.py
huster/__init__.py
huster/server.py
huster/test.py
huster-0.0.6.data/scripts/build_server_scripts
huster-0.0.6.dist-info/licenses/LICENSE
huster-0.0.6.dist-info/METADATA
huster-0.0.6.dist-info/WHEEL
huster-0.0.6.dist-info/entry_points.txt
huster-0.0.6.dist-info/top_level.txt
huster-0.0.6.dist-info/RECORD
