Metadata-Version: 2.4
Name: Huster
Version: 0.0.6
Summary: HTTP Uploading Server Tool.
Home-page: https://github.com/ZQPei/Huster
Author: ZQPei
Author-email: peiziqiang@gmail.com
License: MIT
Platform: all
License-File: LICENSE
Dynamic: author
Dynamic: author-email
Dynamic: description
Dynamic: description-content-type
Dynamic: home-page
Dynamic: license
Dynamic: license-file
Dynamic: platform
Dynamic: summary
